{
  "id": "hltv-108188-m2-inferno",
  "source": {
    "matchUrl": "https://www.hltv.org/matches/2394215/cs-asia-championships-2026-group-a-lower-bracket-semi-final-1-cs-asia-championships-2026",
    "demoFile": "m80-vs-mouz-m2-inferno.dem",
    "tier": "elite",
    "parsedAt": "2026-06-04T04:23:18.229Z"
  },
  "signals": [
    {
      "steamId64": "76561198063336407",
      "rounds": 23,
      "sourceVersion": "analysis-to-account-fixture/0.1",
      "combat": {
        "kills": 17,
        "deaths": 15,
        "assists": 5,
        "effectiveDamage": 2637,
        "openingKills": 0,
        "openingDeaths": 0,
        "multiKills": {
          "two": 0,
          "three": 0,
          "four": 0,
          "five": 0
        },
        "headshotKills": 11,
        "wallbangKills": 0,
        "killsByBuyDelta": null,
        "killsByManState": null
      },
      "trade": {
        "tradeKills": 0,
        "tradedDeaths": 0,
        "deaths": 15,
        "tradedOpeningDeaths": null
      },
      "clutch": {
        "vsOne": {
          "count": 0,
          "won": 0
        },
        "vsTwo": {
          "count": 0,
          "won": 0
        },
        "vsThree": {
          "count": 0,
          "won": 0
        },
        "vsFour": {
          "count": 0,
          "won": 0
        },
        "vsFive": {
          "count": 0,
          "won": 0
        }
      },
      "objective": {
        "plants": 0,
        "defuses": 0,
        "plantsConverted": 0
      },
      "utility": {
        "flashAssists": 0,
        "enemyFlashDurationSeconds": 0,
        "teamFlashDurationSeconds": null,
        "utilityDamage": 0
      }
    },
    {
      "steamId64": "76561198064353169",
      "rounds": 23,
      "sourceVersion": "analysis-to-account-fixture/0.1",
      "combat": {
        "kills": 16,
        "deaths": 12,
        "assists": 3,
        "effectiveDamage": 2274,
        "openingKills": 0,
        "openingDeaths": 0,
        "multiKills": {
          "two": 0,
          "three": 0,
          "four": 0,
          "five": 0
        },
        "headshotKills": 9,
        "wallbangKills": 0,
        "killsByBuyDelta": null,
        "killsByManState": null
      },
      "trade": {
        "tradeKills": 0,
        "tradedDeaths": 0,
        "deaths": 12,
        "tradedOpeningDeaths": null
      },
      "clutch": {
        "vsOne": {
          "count": 0,
          "won": 0
        },
        "vsTwo": {
          "count": 0,
          "won": 0
        },
        "vsThree": {
          "count": 0,
          "won": 0
        },
        "vsFour": {
          "count": 0,
          "won": 0
        },
        "vsFive": {
          "count": 0,
          "won": 0
        }
      },
      "objective": {
        "plants": 0,
        "defuses": 0,
        "plantsConverted": 0
      },
      "utility": {
        "flashAssists": 0,
        "enemyFlashDurationSeconds": 0,
        "teamFlashDurationSeconds": null,
        "utilityDamage": 0
      }
    },
    {
      "steamId64": "76561198176878303",
      "rounds": 23,
      "sourceVersion": "analysis-to-account-fixture/0.1",
      "combat": {
        "kills": 9,
        "deaths": 14,
        "assists": 8,
        "effectiveDamage": 1993,
        "openingKills": 0,
        "openingDeaths": 0,
        "multiKills": {
          "two": 0,
          "three": 0,
          "four": 0,
          "five": 0
        },
        "headshotKills": 9,
        "wallbangKills": 0,
        "killsByBuyDelta": null,
        "killsByManState": null
      },
      "trade": {
        "tradeKills": 0,
        "tradedDeaths": 0,
        "deaths": 14,
        "tradedOpeningDeaths": null
      },
      "clutch": {
        "vsOne": {
          "count": 0,
          "won": 0
        },
        "vsTwo": {
          "count": 0,
          "won": 0
        },
        "vsThree": {
          "count": 0,
          "won": 0
        },
        "vsFour": {
          "count": 0,
          "won": 0
        },
        "vsFive": {
          "count": 0,
          "won": 0
        }
      },
      "objective": {
        "plants": 0,
        "defuses": 0,
        "plantsConverted": 0
      },
      "utility": {
        "flashAssists": 0,
        "enemyFlashDurationSeconds": 0,
        "teamFlashDurationSeconds": null,
        "utilityDamage": 0
      }
    },
    {
      "steamId64": "76561198183003671",
      "rounds": 23,
      "sourceVersion": "analysis-to-account-fixture/0.1",
      "combat": {
        "kills": 13,
        "deaths": 15,
        "assists": 8,
        "effectiveDamage": 1961,
        "openingKills": 0,
        "openingDeaths": 0,
        "multiKills": {
          "two": 0,
          "three": 0,
          "four": 0,
          "five": 0
        },
        "headshotKills": 3,
        "wallbangKills": 0,
        "killsByBuyDelta": null,
        "killsByManState": null
      },
      "trade": {
        "tradeKills": 0,
        "tradedDeaths": 0,
        "deaths": 15,
        "tradedOpeningDeaths": null
      },
      "clutch": {
        "vsOne": {
          "count": 0,
          "won": 0
        },
        "vsTwo": {
          "count": 0,
          "won": 0
        },
        "vsThree": {
          "count": 0,
          "won": 0
        },
        "vsFour": {
          "count": 0,
          "won": 0
        },
        "vsFive": {
          "count": 0,
          "won": 0
        }
      },
      "objective": {
        "plants": 0,
        "defuses": 0,
        "plantsConverted": 0
      },
      "utility": {
        "flashAssists": 0,
        "enemyFlashDurationSeconds": 0,
        "teamFlashDurationSeconds": null,
        "utilityDamage": 0
      }
    },
    {
      "steamId64": "76561198184153575",
      "rounds": 23,
      "sourceVersion": "analysis-to-account-fixture/0.1",
      "combat": {
        "kills": 7,
        "deaths": 15,
        "assists": 3,
        "effectiveDamage": 1119,
        "openingKills": 0,
        "openingDeaths": 0,
        "multiKills": {
          "two": 0,
          "three": 0,
          "four": 0,
          "five": 0
        },
        "headshotKills": 4,
        "wallbangKills": 0,
        "killsByBuyDelta": null,
        "killsByManState": null
      },
      "trade": {
        "tradeKills": 0,
        "tradedDeaths": 0,
        "deaths": 15,
        "tradedOpeningDeaths": null
      },
      "clutch": {
        "vsOne": {
          "count": 0,
          "won": 0
        },
        "vsTwo": {
          "count": 0,
          "won": 0
        },
        "vsThree": {
          "count": 0,
          "won": 0
        },
        "vsFour": {
          "count": 0,
          "won": 0
        },
        "vsFive": {
          "count": 0,
          "won": 0
        }
      },
      "objective": {
        "plants": 0,
        "defuses": 0,
        "plantsConverted": 0
      },
      "utility": {
        "flashAssists": 0,
        "enemyFlashDurationSeconds": 0,
        "teamFlashDurationSeconds": null,
        "utilityDamage": 0
      }
    },
    {
      "steamId64": "76561198190463461",
      "rounds": 23,
      "sourceVersion": "analysis-to-account-fixture/0.1",
      "combat": {
        "kills": 13,
        "deaths": 12,
        "assists": 6,
        "effectiveDamage": 1604,
        "openingKills": 0,
        "openingDeaths": 0,
        "multiKills": {
          "two": 0,
          "three": 0,
          "four": 0,
          "five": 0
        },
        "headshotKills": 5,
        "wallbangKills": 0,
        "killsByBuyDelta": null,
        "killsByManState": null
      },
      "trade": {
        "tradeKills": 0,
        "tradedDeaths": 0,
        "deaths": 12,
        "tradedOpeningDeaths": null
      },
      "clutch": {
        "vsOne": {
          "count": 0,
          "won": 0
        },
        "vsTwo": {
          "count": 0,
          "won": 0
        },
        "vsThree": {
          "count": 0,
          "won": 0
        },
        "vsFour": {
          "count": 0,
          "won": 0
        },
        "vsFive": {
          "count": 0,
          "won": 0
        }
      },
      "objective": {
        "plants": 0,
        "defuses": 0,
        "plantsConverted": 0
      },
      "utility": {
        "flashAssists": 0,
        "enemyFlashDurationSeconds": 0,
        "teamFlashDurationSeconds": null,
        "utilityDamage": 0
      }
    },
    {
      "steamId64": "76561198193174134",
      "rounds": 23,
      "sourceVersion": "analysis-to-account-fixture/0.1",
      "combat": {
        "kills": 23,
        "deaths": 13,
        "assists": 4,
        "effectiveDamage": 3152,
        "openingKills": 0,
        "openingDeaths": 0,
        "multiKills": {
          "two": 0,
          "three": 0,
          "four": 0,
          "five": 0
        },
        "headshotKills": 12,
        "wallbangKills": 0,
        "killsByBuyDelta": null,
        "killsByManState": null
      },
      "trade": {
        "tradeKills": 0,
        "tradedDeaths": 0,
        "deaths": 13,
        "tradedOpeningDeaths": null
      },
      "clutch": {
        "vsOne": {
          "count": 0,
          "won": 0
        },
        "vsTwo": {
          "count": 0,
          "won": 0
        },
        "vsThree": {
          "count": 0,
          "won": 0
        },
        "vsFour": {
          "count": 0,
          "won": 0
        },
        "vsFive": {
          "count": 0,
          "won": 0
        }
      },
      "objective": {
        "plants": 0,
        "defuses": 0,
        "plantsConverted": 0
      },
      "utility": {
        "flashAssists": 0,
        "enemyFlashDurationSeconds": 0,
        "teamFlashDurationSeconds": null,
        "utilityDamage": 0
      }
    },
    {
      "steamId64": "76561198337484196",
      "rounds": 23,
      "sourceVersion": "analysis-to-account-fixture/0.1",
      "combat": {
        "kills": 22,
        "deaths": 19,
        "assists": 7,
        "effectiveDamage": 3272,
        "openingKills": 0,
        "openingDeaths": 0,
        "multiKills": {
          "two": 0,
          "three": 0,
          "four": 0,
          "five": 0
        },
        "headshotKills": 14,
        "wallbangKills": 0,
        "killsByBuyDelta": null,
        "killsByManState": null
      },
      "trade": {
        "tradeKills": 0,
        "tradedDeaths": 0,
        "deaths": 19,
        "tradedOpeningDeaths": null
      },
      "clutch": {
        "vsOne": {
          "count": 0,
          "won": 0
        },
        "vsTwo": {
          "count": 0,
          "won": 0
        },
        "vsThree": {
          "count": 0,
          "won": 0
        },
        "vsFour": {
          "count": 0,
          "won": 0
        },
        "vsFive": {
          "count": 0,
          "won": 0
        }
      },
      "objective": {
        "plants": 0,
        "defuses": 0,
        "plantsConverted": 0
      },
      "utility": {
        "flashAssists": 0,
        "enemyFlashDurationSeconds": 0,
        "teamFlashDurationSeconds": null,
        "utilityDamage": 0
      }
    },
    {
      "steamId64": "76561198355739212",
      "rounds": 23,
      "sourceVersion": "analysis-to-account-fixture/0.1",
      "combat": {
        "kills": 8,
        "deaths": 15,
        "assists": 6,
        "effectiveDamage": 1099,
        "openingKills": 0,
        "openingDeaths": 0,
        "multiKills": {
          "two": 0,
          "three": 0,
          "four": 0,
          "five": 0
        },
        "headshotKills": 3,
        "wallbangKills": 0,
        "killsByBuyDelta": null,
        "killsByManState": null
      },
      "trade": {
        "tradeKills": 0,
        "tradedDeaths": 0,
        "deaths": 15,
        "tradedOpeningDeaths": null
      },
      "clutch": {
        "vsOne": {
          "count": 0,
          "won": 0
        },
        "vsTwo": {
          "count": 0,
          "won": 0
        },
        "vsThree": {
          "count": 0,
          "won": 0
        },
        "vsFour": {
          "count": 0,
          "won": 0
        },
        "vsFive": {
          "count": 0,
          "won": 0
        }
      },
      "objective": {
        "plants": 0,
        "defuses": 0,
        "plantsConverted": 0
      },
      "utility": {
        "flashAssists": 0,
        "enemyFlashDurationSeconds": 0,
        "teamFlashDurationSeconds": null,
        "utilityDamage": 0
      }
    },
    {
      "steamId64": "76561198998266210",
      "rounds": 23,
      "sourceVersion": "analysis-to-account-fixture/0.1",
      "combat": {
        "kills": 16,
        "deaths": 14,
        "assists": 3,
        "effectiveDamage": 2132,
        "openingKills": 0,
        "openingDeaths": 0,
        "multiKills": {
          "two": 0,
          "three": 0,
          "four": 0,
          "five": 0
        },
        "headshotKills": 11,
        "wallbangKills": 0,
        "killsByBuyDelta": null,
        "killsByManState": null
      },
      "trade": {
        "tradeKills": 0,
        "tradedDeaths": 0,
        "deaths": 14,
        "tradedOpeningDeaths": null
      },
      "clutch": {
        "vsOne": {
          "count": 0,
          "won": 0
        },
        "vsTwo": {
          "count": 0,
          "won": 0
        },
        "vsThree": {
          "count": 0,
          "won": 0
        },
        "vsFour": {
          "count": 0,
          "won": 0
        },
        "vsFive": {
          "count": 0,
          "won": 0
        }
      },
      "objective": {
        "plants": 0,
        "defuses": 0,
        "plantsConverted": 0
      },
      "utility": {
        "flashAssists": 0,
        "enemyFlashDurationSeconds": 0,
        "teamFlashDurationSeconds": null,
        "utilityDamage": 0
      }
    }
  ],
  "expected": {
    "tolerance": 0.000001,
    "players": [
      {
        "steamId64": "76561198063336407",
        "valueAccountsRR": 0.940696,
        "cohortRR": 1.078258
      },
      {
        "steamId64": "76561198064353169",
        "valueAccountsRR": 0.931391,
        "cohortRR": 1.196641
      },
      {
        "steamId64": "76561198176878303",
        "valueAccountsRR": 0.686043,
        "cohortRR": 0.894351
      },
      {
        "steamId64": "76561198183003671",
        "valueAccountsRR": 0.75687,
        "cohortRR": 0.915027
      },
      {
        "steamId64": "76561198184153575",
        "valueAccountsRR": 0.503565,
        "cohortRR": 0.690102
      },
      {
        "steamId64": "76561198190463461",
        "valueAccountsRR": 0.772261,
        "cohortRR": 1.055339
      },
      {
        "steamId64": "76561198193174134",
        "valueAccountsRR": 1.192652,
        "cohortRR": 1.386416
      },
      {
        "steamId64": "76561198337484196",
        "valueAccountsRR": 1.060478,
        "cohortRR": 1.01576
      },
      {
        "steamId64": "76561198355739212",
        "valueAccountsRR": 0.52487,
        "cohortRR": 0.709019
      },
      {
        "steamId64": "76561198998266210",
        "valueAccountsRR": 0.871565,
        "cohortRR": 1.059087
      }
    ]
  }
}
